mangadex_dl/__init__.py
mangadex_dl/chapter.py
mangadex_dl/cli.py
mangadex_dl/constants.py
mangadex_dl/helper.py
mangadex_dl/library.py
mangadex_dl/manga.py
mangadex_dl/organiser.py
mangadex_dl/static/library.csv
mangadex_dl-3.5.0.dist-info/LICENSE
mangadex_dl-3.5.0.dist-info/METADATA
mangadex_dl-3.5.0.dist-info/WHEEL
mangadex_dl-3.5.0.dist-info/entry_points.txt
mangadex_dl-3.5.0.dist-info/top_level.txt
mangadex_dl-3.5.0.dist-info/RECORD
