Metadata-Version: 2.1
Name: mangadex-dl
Version: 3.5.0
Summary: A Python CLI that downloads manga from mangadex.org as image or PDF
Home-page: https://github.com/john-erinjery/mangadex-dl/
Author: John Erinjery
Author-email: jancyvinod415@gmail.com
License: MIT
Classifier: Development Status :: 4 - Beta
Classifier: Environment :: Console
Classifier: Intended Audience :: Customer Service
Classifier: License :: OSI Approved :: MIT License
Classifier: Natural Language :: English
Classifier: Operating System :: OS Independent
Classifier: Programming Language :: Python :: 3.10
Classifier: Topic :: Internet
Classifier: Topic :: Software Development :: Libraries
Classifier: Topic :: Software Development :: Libraries :: Python Modules
Classifier: Topic :: Utilities
Requires-Python: >=3.7
License-File: LICENSE
Requires-Dist: mangadex (==2.5.2)
Requires-Dist: Pillow (==9.4.0)
Requires-Dist: PyPDF2 (==3.0.1)
Requires-Dist: requests (==2.28.2)
Requires-Dist: prettytable (==3.7.0)
